{
    "bot_name": "Math_Probability_V3",
    "market": "SENSEX",
    "front_scores": [
        6.0,
        11.0,
        10.0,
        14.0,
        13.0,
        1.5,
        15.0,
        2.5,
        22.0,
        4.5
    ],
    "back_scores": [
        13.0,
        14.5,
        11.5,
        5.0,
        10.0,
        10.0,
        4.0,
        9.5,
        10.5,
        11.0
    ],
    "top_front": [
        8,
        6,
        3,
        4,
        1
    ],
    "top_back": [
        1,
        0,
        2,
        9,
        8
    ],
    "status": "success"
}