{
    "bot_name": "AI_Pattern_V1",
    "market": "FTSE",
    "top_digits": [
        "9",
        "2",
        "3",
        "4",
        "5",
        "1",
        "0",
        "6",
        "7",
        "8"
    ],
    "raw_scores": [
        0.12469458067581095,
        0.14426000055360627,
        0.4782857811705151,
        0.2101717724166144,
        0.1986820128006888,
        0.1772115296313115,
        0.1095866175512495,
        0.08059595537462289,
        0.05347826817488554,
        0.5626579098866541
    ],
    "status": "success"
}